{  
  "id": "npg9sepoig934ngf",
  "name":"Faculty of Arts",
  "shortName":"",
  "slug":"facultyofarts",
  "schoolSlug": "universityofwaterloo", 
  "about":"Waterloo Arts is committed to education and scholarship in the humanities, social sciences, languages and cultures, and the fine and performing arts for the benefit of the people of Ontario, of Canada, and of the world beyond our borders. The education students receive in the Faculty of Arts, including its federated university and affiliated university colleges, offers them the tools and skills they need to succeed in today's diverse and changing world, while empowering them intellectually with the rich tradition of ideas and techniques of understanding that shape cultures and civilizations. The Faculty is a community dedicated to producing research of high academic merit and impact. The driving force behind all our work is a deep commitment to curiosity, creativity, and the desire to understand - and engage - the world.",
  "undergradPopulation":"",
  "gradPopulation":"",
  "avgAdm":"Low 80s",
  "dateEstablished":"",
  "numPrograms":"",
  "degree": "", 
  "degreeAbbrev": "", 
  "applicationProcess":"",
  "schoolId":"",
  "internship": {
        "earnings": "$50,000 to $90,000 over 6 work terms", 
        "general": "Waterloo hosts the largest co-op program on the planet, with connections to over 4,500 employers. As an engineering or architecture student at Waterloo you'll automatically be entered into the co-op program. Throughout your degree, you'll gain up to two years of real-world experience, build connections in industry and strengthen your professional skills with WatPD-Engineering, an online program that covers r\u00e9sum\u00e9 writing, networking and more. On average, engineering students earn $50,000 to $90,000 over six work terms, helping to pay for tuition, books and living expenses.", 
        "specific": "You will be in either Stream 4 or Stream 8. You will be assigned to a stream in late June when classes are scheduled."
  }, 
  "importantDates": [
      {
         "date": "September 19, 2014", 
         "description": "Ontario Universities' Fair in Toronto begins",
         "type": "event"
      }, 
      
  ],
  "metaData":{  
    "dateModified":"",
    "dateCreated":"",
    "yearValid":2015
  },
  "contacts": [
    {  
      "name":"Philippe Bezaire, Associate Director of Admissions",
      "email":"admissions@engmail.uwaterloo.ca",
      "phoneNum":"519-888-4894",
      "website":"",
      "facebook":"",
      "twitter":"",
      "linkedin":"",
      "extraInfo":"Office: CPH 1320"

    }
  ],
  "images":[  
      {  "type":"misc",
         "descriptor":"image1",
         "link":"https://c2.staticflickr.com/5/4128/5158350265_d6126ed1af_b.jpg"
      },
      {  "type":"misc",
         "descriptor":"image2",
         "link":"http://www.uwimprint.ca/uploads/2012/06/hh.png"
      },
      {  "type":"misc",
         "descriptor":"image3",
         "link":"http://img.ffffound.com/static-data/assets/6/9a7a010f017f7219b50b1147e6cde6855a263865_m.jpg"
      },
      {  "type":"misc",
         "descriptor":"image3",
         "link":"https://c2.staticflickr.com/2/1635/25370109443_bb2b634b9a_b.jpg"
      }
  ],
  "location":{  
    "address":"200 University Avenue West",
    "apt":"",
    "unit":"",
    "city":"Waterloo",
    "region":"Ontario",
    "postalCode":"N2L3G1",
    "country":"Canada",
    "latitude":43.4689,
    "longitude":-80.5400
  }
}